[
  {
    "pathId": 1,
    "symbolicInputs": {
      "user_choice": 0
    },
    "constraints": [
      "(0<=user_choice)&&(user_choice<5)",
      "user_choice==0"
    ],
    "executionTime": 1537
  },
  {
    "pathId": 2,
    "symbolicInputs": {
      "user_choice": 1
    },
    "constraints": [
      "(0<=user_choice)&&(user_choice<5)",
      "user_choice==1"
    ],
    "executionTime": 49
  },
  {
    "pathId": 3,
    "symbolicInputs": {
      "user_choice": 2
    },
    "constraints": [
      "(0<=user_choice)&&(user_choice<5)",
      "user_choice==2"
    ],
    "executionTime": 38
  },
  {
    "pathId": 4,
    "symbolicInputs": {
      "user_choice": 3
    },
    "constraints": [
      "(0<=user_choice)&&(user_choice<5)",
      "user_choice==3"
    ],
    "executionTime": 35
  },
  {
    "pathId": 5,
    "symbolicInputs": {
      "user_choice": 4
    },
    "constraints": [
      "(0<=user_choice)&&(user_choice<5)",
      "user_choice==4"
    ],
    "executionTime": 25
  },
  {
    "pathId": 6,
    "symbolicInputs": {
      "user_choice": 5
    },
    "constraints": [
      "(0<=user_choice)&&(user_choice<5)",
      "user_choice==5"
    ],
    "executionTime": 2
  },
  {
    "pathId": 7,
    "symbolicInputs": {
      "user_choice": 6
    },
    "constraints": [
      "(0<=user_choice)&&(user_choice<5)",
      "user_choice==6"
    ],
    "executionTime": 2
  },
  {
    "pathId": 8,
    "symbolicInputs": {
      "user_choice": 7
    },
    "constraints": [
      "(0<=user_choice)&&(user_choice<5)",
      "user_choice==7"
    ],
    "executionTime": 1
  },
  {
    "pathId": 9,
    "symbolicInputs": {
      "user_choice": 8
    },
    "constraints": [
      "(0<=user_choice)&&(user_choice<5)",
      "user_choice==8"
    ],
    "executionTime": 0
  },
  {
    "pathId": 10,
    "symbolicInputs": {
      "user_choice": 9
    },
    "constraints": [
      "(0<=user_choice)&&(user_choice<5)",
      "user_choice==9"
    ],
    "executionTime": 1
  },
  {
    "pathId": 11,
    "symbolicInputs": {
      "user_choice": 10
    },
    "constraints": [
      "(0<=user_choice)&&(user_choice<5)",
      "user_choice==10"
    ],
    "executionTime": 0
  },
  {
    "pathId": 12,
    "symbolicInputs": {
      "user_choice": 11
    },
    "constraints": [
      "(0<=user_choice)&&(user_choice<5)",
      "user_choice==11"
    ],
    "executionTime": 1
  },
  {
    "pathId": 13,
    "symbolicInputs": {
      "user_choice": 12
    },
    "constraints": [
      "(0<=user_choice)&&(user_choice<5)",
      "user_choice==12"
    ],
    "executionTime": 0
  },
  {
    "pathId": 14,
    "symbolicInputs": {
      "user_choice": 13
    },
    "constraints": [
      "(0<=user_choice)&&(user_choice<5)",
      "user_choice==13"
    ],
    "executionTime": 1
  },
  {
    "pathId": 15,
    "symbolicInputs": {
      "user_choice": 14
    },
    "constraints": [
      "(0<=user_choice)&&(user_choice<5)",
      "user_choice==14"
    ],
    "executionTime": 2
  },
  {
    "pathId": 16,
    "symbolicInputs": {
      "user_choice": 15
    },
    "constraints": [
      "(0<=user_choice)&&(user_choice<5)",
      "user_choice==15"
    ],
    "executionTime": 2
  },
  {
    "pathId": 17,
    "symbolicInputs": {
      "user_choice": 16
    },
    "constraints": [
      "(0<=user_choice)&&(user_choice<5)",
      "user_choice==16"
    ],
    "executionTime": 1
  },
  {
    "pathId": 18,
    "symbolicInputs": {
      "user_choice": 17
    },
    "constraints": [
      "(0<=user_choice)&&(user_choice<5)",
      "user_choice==17"
    ],
    "executionTime": 1
  },
  {
    "pathId": 19,
    "symbolicInputs": {
      "user_choice": 18
    },
    "constraints": [
      "(0<=user_choice)&&(user_choice<5)",
      "user_choice==18"
    ],
    "executionTime": 1
  },
  {
    "pathId": 20,
    "symbolicInputs": {
      "user_choice": 19
    },
    "constraints": [
      "(0<=user_choice)&&(user_choice<5)",
      "user_choice==19"
    ],
    "executionTime": 1
  },
  {
    "pathId": 21,
    "symbolicInputs": {
      "user_choice": 20
    },
    "constraints": [
      "(0<=user_choice)&&(user_choice<5)",
      "user_choice==20"
    ],
    "executionTime": 0
  },
  {
    "pathId": 22,
    "symbolicInputs": {
      "user_choice": 21
    },
    "constraints": [
      "(0<=user_choice)&&(user_choice<5)",
      "user_choice==21"
    ],
    "executionTime": 1
  },
  {
    "pathId": 23,
    "symbolicInputs": {
      "user_choice": 22
    },
    "constraints": [
      "(0<=user_choice)&&(user_choice<5)",
      "user_choice==22"
    ],
    "executionTime": 1
  },
  {
    "pathId": 24,
    "symbolicInputs": {
      "user_choice": 23
    },
    "constraints": [
      "(0<=user_choice)&&(user_choice<5)",
      "user_choice==23"
    ],
    "executionTime": 1
  },
  {
    "pathId": 25,
    "symbolicInputs": {
      "user_choice": 24
    },
    "constraints": [
      "(0<=user_choice)&&(user_choice<5)",
      "user_choice==24"
    ],
    "executionTime": 1
  },
  {
    "pathId": 26,
    "symbolicInputs": {
      "user_choice": 25
    },
    "constraints": [
      "(0<=user_choice)&&(user_choice<5)",
      "user_choice==25"
    ],
    "executionTime": 0
  },
  {
    "pathId": 27,
    "symbolicInputs": {
      "user_choice": 26
    },
    "constraints": [
      "(0<=user_choice)&&(user_choice<5)",
      "user_choice==26"
    ],
    "executionTime": 1
  },
  {
    "pathId": 28,
    "symbolicInputs": {
      "user_choice": 27
    },
    "constraints": [
      "(0<=user_choice)&&(user_choice<5)",
      "user_choice==27"
    ],
    "executionTime": 1
  },
  {
    "pathId": 29,
    "symbolicInputs": {
      "user_choice": 28
    },
    "constraints": [
      "(0<=user_choice)&&(user_choice<5)",
      "user_choice==28"
    ],
    "executionTime": 0
  },
  {
    "pathId": 30,
    "symbolicInputs": {
      "user_choice": 29
    },
    "constraints": [
      "(0<=user_choice)&&(user_choice<5)",
      "user_choice==29"
    ],
    "executionTime": 1
  },
  {
    "pathId": 31,
    "symbolicInputs": {
      "user_choice": 30
    },
    "constraints": [
      "(0<=user_choice)&&(user_choice<5)",
      "user_choice==30"
    ],
    "executionTime": 1
  },
  {
    "pathId": 32,
    "symbolicInputs": {
      "user_choice": 31
    },
    "constraints": [
      "(0<=user_choice)&&(user_choice<5)",
      "user_choice==31"
    ],
    "executionTime": 1
  },
  {
    "pathId": 33,
    "symbolicInputs": {
      "user_choice": 32
    },
    "constraints": [
      "(0<=user_choice)&&(user_choice<5)",
      "user_choice==32"
    ],
    "executionTime": 1
  },
  {
    "pathId": 34,
    "symbolicInputs": {
      "user_choice": 33
    },
    "constraints": [
      "(0<=user_choice)&&(user_choice<5)",
      "user_choice==33"
    ],
    "executionTime": 0
  },
  {
    "pathId": 35,
    "symbolicInputs": {
      "user_choice": 34
    },
    "constraints": [
      "(0<=user_choice)&&(user_choice<5)",
      "user_choice==34"
    ],
    "executionTime": 1
  },
  {
    "pathId": 36,
    "symbolicInputs": {
      "user_choice": 35
    },
    "constraints": [
      "(0<=user_choice)&&(user_choice<5)",
      "user_choice==35"
    ],
    "executionTime": 1
  },
  {
    "pathId": 37,
    "symbolicInputs": {
      "user_choice": 36
    },
    "constraints": [
      "(0<=user_choice)&&(user_choice<5)",
      "user_choice==36"
    ],
    "executionTime": 0
  },
  {
    "pathId": 38,
    "symbolicInputs": {
      "user_choice": 37
    },
    "constraints": [
      "(0<=user_choice)&&(user_choice<5)",
      "user_choice==37"
    ],
    "executionTime": 1
  },
  {
    "pathId": 39,
    "symbolicInputs": {
      "user_choice": 38
    },
    "constraints": [
      "(0<=user_choice)&&(user_choice<5)",
      "user_choice==38"
    ],
    "executionTime": 0
  },
  {
    "pathId": 40,
    "symbolicInputs": {
      "user_choice": 39
    },
    "constraints": [
      "(0<=user_choice)&&(user_choice<5)",
      "user_choice==39"
    ],
    "executionTime": 1
  },
  {
    "pathId": 41,
    "symbolicInputs": {
      "user_choice": 40
    },
    "constraints": [
      "(0<=user_choice)&&(user_choice<5)",
      "user_choice==40"
    ],
    "executionTime": 0
  },
  {
    "pathId": 42,
    "symbolicInputs": {
      "user_choice": 41
    },
    "constraints": [
      "(0<=user_choice)&&(user_choice<5)",
      "user_choice==41"
    ],
    "executionTime": 1
  },
  {
    "pathId": 43,
    "symbolicInputs": {
      "user_choice": 42
    },
    "constraints": [
      "(0<=user_choice)&&(user_choice<5)",
      "user_choice==42"
    ],
    "executionTime": 1
  },
  {
    "pathId": 44,
    "symbolicInputs": {
      "user_choice": 43
    },
    "constraints": [
      "(0<=user_choice)&&(user_choice<5)",
      "user_choice==43"
    ],
    "executionTime": 0
  },
  {
    "pathId": 45,
    "symbolicInputs": {
      "user_choice": 44
    },
    "constraints": [
      "(0<=user_choice)&&(user_choice<5)",
      "user_choice==44"
    ],
    "executionTime": 2
  },
  {
    "pathId": 46,
    "symbolicInputs": {
      "user_choice": 45
    },
    "constraints": [
      "(0<=user_choice)&&(user_choice<5)",
      "user_choice==45"
    ],
    "executionTime": 0
  },
  {
    "pathId": 47,
    "symbolicInputs": {
      "user_choice": 46
    },
    "constraints": [
      "(0<=user_choice)&&(user_choice<5)",
      "user_choice==46"
    ],
    "executionTime": 0
  },
  {
    "pathId": 48,
    "symbolicInputs": {
      "user_choice": 47
    },
    "constraints": [
      "(0<=user_choice)&&(user_choice<5)",
      "user_choice==47"
    ],
    "executionTime": 0
  },
  {
    "pathId": 49,
    "symbolicInputs": {
      "user_choice": 48
    },
    "constraints": [
      "(0<=user_choice)&&(user_choice<5)",
      "user_choice==48"
    ],
    "executionTime": 0
  },
  {
    "pathId": 50,
    "symbolicInputs": {
      "user_choice": 49
    },
    "constraints": [
      "(0<=user_choice)&&(user_choice<5)",
      "user_choice==49"
    ],
    "executionTime": 0
  },
  {
    "pathId": 51,
    "symbolicInputs": {
      "user_choice": 50
    },
    "constraints": [
      "(0<=user_choice)&&(user_choice<5)",
      "user_choice==50"
    ],
    "executionTime": 0
  },
  {
    "pathId": 52,
    "symbolicInputs": {
      "user_choice": 51
    },
    "constraints": [
      "(0<=user_choice)&&(user_choice<5)",
      "user_choice==51"
    ],
    "executionTime": 0
  },
  {
    "pathId": 53,
    "symbolicInputs": {
      "user_choice": 52
    },
    "constraints": [
      "(0<=user_choice)&&(user_choice<5)",
      "user_choice==52"
    ],
    "executionTime": 0
  },
  {
    "pathId": 54,
    "symbolicInputs": {
      "user_choice": 53
    },
    "constraints": [
      "(0<=user_choice)&&(user_choice<5)",
      "user_choice==53"
    ],
    "executionTime": 0
  },
  {
    "pathId": 55,
    "symbolicInputs": {
      "user_choice": 54
    },
    "constraints": [
      "(0<=user_choice)&&(user_choice<5)",
      "user_choice==54"
    ],
    "executionTime": 0
  },
  {
    "pathId": 56,
    "symbolicInputs": {
      "user_choice": 55
    },
    "constraints": [
      "(0<=user_choice)&&(user_choice<5)",
      "user_choice==55"
    ],
    "executionTime": 0
  },
  {
    "pathId": 57,
    "symbolicInputs": {
      "user_choice": 56
    },
    "constraints": [
      "(0<=user_choice)&&(user_choice<5)",
      "user_choice==56"
    ],
    "executionTime": 0
  },
  {
    "pathId": 58,
    "symbolicInputs": {
      "user_choice": 57
    },
    "constraints": [
      "(0<=user_choice)&&(user_choice<5)",
      "user_choice==57"
    ],
    "executionTime": 0
  },
  {
    "pathId": 59,
    "symbolicInputs": {
      "user_choice": 58
    },
    "constraints": [
      "(0<=user_choice)&&(user_choice<5)",
      "user_choice==58"
    ],
    "executionTime": 0
  },
  {
    "pathId": 60,
    "symbolicInputs": {
      "user_choice": 59
    },
    "constraints": [
      "(0<=user_choice)&&(user_choice<5)",
      "user_choice==59"
    ],
    "executionTime": 0
  },
  {
    "pathId": 61,
    "symbolicInputs": {
      "user_choice": 60
    },
    "constraints": [
      "(0<=user_choice)&&(user_choice<5)",
      "user_choice==60"
    ],
    "executionTime": 0
  },
  {
    "pathId": 62,
    "symbolicInputs": {
      "user_choice": 61
    },
    "constraints": [
      "(0<=user_choice)&&(user_choice<5)",
      "user_choice==61"
    ],
    "executionTime": 0
  },
  {
    "pathId": 63,
    "symbolicInputs": {
      "user_choice": 62
    },
    "constraints": [
      "(0<=user_choice)&&(user_choice<5)",
      "user_choice==62"
    ],
    "executionTime": 0
  },
  {
    "pathId": 64,
    "symbolicInputs": {
      "user_choice": 63
    },
    "constraints": [
      "(0<=user_choice)&&(user_choice<5)",
      "user_choice==63"
    ],
    "executionTime": 0
  },
  {
    "pathId": 65,
    "symbolicInputs": {
      "user_choice": 64
    },
    "constraints": [
      "(0<=user_choice)&&(user_choice<5)",
      "user_choice==64"
    ],
    "executionTime": 0
  },
  {
    "pathId": 66,
    "symbolicInputs": {
      "user_choice": 65
    },
    "constraints": [
      "(0<=user_choice)&&(user_choice<5)",
      "user_choice==65"
    ],
    "executionTime": 0
  },
  {
    "pathId": 67,
    "symbolicInputs": {
      "user_choice": 66
    },
    "constraints": [
      "(0<=user_choice)&&(user_choice<5)",
      "user_choice==66"
    ],
    "executionTime": 15
  },
  {
    "pathId": 68,
    "symbolicInputs": {
      "user_choice": 67
    },
    "constraints": [
      "(0<=user_choice)&&(user_choice<5)",
      "user_choice==67"
    ],
    "executionTime": 0
  },
  {
    "pathId": 69,
    "symbolicInputs": {
      "user_choice": 68
    },
    "constraints": [
      "(0<=user_choice)&&(user_choice<5)",
      "user_choice==68"
    ],
    "executionTime": 0
  },
  {
    "pathId": 70,
    "symbolicInputs": {
      "user_choice": 69
    },
    "constraints": [
      "(0<=user_choice)&&(user_choice<5)",
      "user_choice==69"
    ],
    "executionTime": 0
  },
  {
    "pathId": 71,
    "symbolicInputs": {
      "user_choice": 70
    },
    "constraints": [
      "(0<=user_choice)&&(user_choice<5)",
      "user_choice==70"
    ],
    "executionTime": 0
  },
  {
    "pathId": 72,
    "symbolicInputs": {
      "user_choice": 71
    },
    "constraints": [
      "(0<=user_choice)&&(user_choice<5)",
      "user_choice==71"
    ],
    "executionTime": 0
  },
  {
    "pathId": 73,
    "symbolicInputs": {
      "user_choice": 72
    },
    "constraints": [
      "(0<=user_choice)&&(user_choice<5)",
      "user_choice==72"
    ],
    "executionTime": 0
  },
  {
    "pathId": 74,
    "symbolicInputs": {
      "user_choice": 73
    },
    "constraints": [
      "(0<=user_choice)&&(user_choice<5)",
      "user_choice==73"
    ],
    "executionTime": 0
  },
  {
    "pathId": 75,
    "symbolicInputs": {
      "user_choice": 74
    },
    "constraints": [
      "(0<=user_choice)&&(user_choice<5)",
      "user_choice==74"
    ],
    "executionTime": 0
  },
  {
    "pathId": 76,
    "symbolicInputs": {
      "user_choice": 75
    },
    "constraints": [
      "(0<=user_choice)&&(user_choice<5)",
      "user_choice==75"
    ],
    "executionTime": 0
  },
  {
    "pathId": 77,
    "symbolicInputs": {
      "user_choice": 76
    },
    "constraints": [
      "(0<=user_choice)&&(user_choice<5)",
      "user_choice==76"
    ],
    "executionTime": 0
  },
  {
    "pathId": 78,
    "symbolicInputs": {
      "user_choice": 77
    },
    "constraints": [
      "(0<=user_choice)&&(user_choice<5)",
      "user_choice==77"
    ],
    "executionTime": 0
  },
  {
    "pathId": 79,
    "symbolicInputs": {
      "user_choice": 78
    },
    "constraints": [
      "(0<=user_choice)&&(user_choice<5)",
      "user_choice==78"
    ],
    "executionTime": 0
  },
  {
    "pathId": 80,
    "symbolicInputs": {
      "user_choice": 79
    },
    "constraints": [
      "(0<=user_choice)&&(user_choice<5)",
      "user_choice==79"
    ],
    "executionTime": 0
  },
  {
    "pathId": 81,
    "symbolicInputs": {
      "user_choice": 80
    },
    "constraints": [
      "(0<=user_choice)&&(user_choice<5)",
      "user_choice==80"
    ],
    "executionTime": 0
  },
  {
    "pathId": 82,
    "symbolicInputs": {
      "user_choice": 81
    },
    "constraints": [
      "(0<=user_choice)&&(user_choice<5)",
      "user_choice==81"
    ],
    "executionTime": 0
  },
  {
    "pathId": 83,
    "symbolicInputs": {
      "user_choice": 82
    },
    "constraints": [
      "(0<=user_choice)&&(user_choice<5)",
      "user_choice==82"
    ],
    "executionTime": 10
  },
  {
    "pathId": 84,
    "symbolicInputs": {
      "user_choice": 83
    },
    "constraints": [
      "(0<=user_choice)&&(user_choice<5)",
      "user_choice==83"
    ],
    "executionTime": 0
  },
  {
    "pathId": 85,
    "symbolicInputs": {
      "user_choice": 84
    },
    "constraints": [
      "(0<=user_choice)&&(user_choice<5)",
      "user_choice==84"
    ],
    "executionTime": 0
  },
  {
    "pathId": 86,
    "symbolicInputs": {
      "user_choice": 85
    },
    "constraints": [
      "(0<=user_choice)&&(user_choice<5)",
      "user_choice==85"
    ],
    "executionTime": 0
  },
  {
    "pathId": 87,
    "symbolicInputs": {
      "user_choice": 86
    },
    "constraints": [
      "(0<=user_choice)&&(user_choice<5)",
      "user_choice==86"
    ],
    "executionTime": 0
  },
  {
    "pathId": 88,
    "symbolicInputs": {
      "user_choice": 87
    },
    "constraints": [
      "(0<=user_choice)&&(user_choice<5)",
      "user_choice==87"
    ],
    "executionTime": 0
  },
  {
    "pathId": 89,
    "symbolicInputs": {
      "user_choice": 88
    },
    "constraints": [
      "(0<=user_choice)&&(user_choice<5)",
      "user_choice==88"
    ],
    "executionTime": 6
  },
  {
    "pathId": 90,
    "symbolicInputs": {
      "user_choice": 89
    },
    "constraints": [
      "(0<=user_choice)&&(user_choice<5)",
      "user_choice==89"
    ],
    "executionTime": 0
  },
  {
    "pathId": 91,
    "symbolicInputs": {
      "user_choice": 90
    },
    "constraints": [
      "(0<=user_choice)&&(user_choice<5)",
      "user_choice==90"
    ],
    "executionTime": 0
  },
  {
    "pathId": 92,
    "symbolicInputs": {
      "user_choice": 91
    },
    "constraints": [
      "(0<=user_choice)&&(user_choice<5)",
      "user_choice==91"
    ],
    "executionTime": 0
  },
  {
    "pathId": 93,
    "symbolicInputs": {
      "user_choice": 92
    },
    "constraints": [
      "(0<=user_choice)&&(user_choice<5)",
      "user_choice==92"
    ],
    "executionTime": 0
  },
  {
    "pathId": 94,
    "symbolicInputs": {
      "user_choice": 93
    },
    "constraints": [
      "(0<=user_choice)&&(user_choice<5)",
      "user_choice==93"
    ],
    "executionTime": 0
  },
  {
    "pathId": 95,
    "symbolicInputs": {
      "user_choice": 94
    },
    "constraints": [
      "(0<=user_choice)&&(user_choice<5)",
      "user_choice==94"
    ],
    "executionTime": 0
  },
  {
    "pathId": 96,
    "symbolicInputs": {
      "user_choice": 95
    },
    "constraints": [
      "(0<=user_choice)&&(user_choice<5)",
      "user_choice==95"
    ],
    "executionTime": 0
  },
  {
    "pathId": 97,
    "symbolicInputs": {
      "user_choice": 96
    },
    "constraints": [
      "(0<=user_choice)&&(user_choice<5)",
      "user_choice==96"
    ],
    "executionTime": 0
  },
  {
    "pathId": 98,
    "symbolicInputs": {
      "user_choice": 97
    },
    "constraints": [
      "(0<=user_choice)&&(user_choice<5)",
      "user_choice==97"
    ],
    "executionTime": 0
  },
  {
    "pathId": 99,
    "symbolicInputs": {
      "user_choice": 98
    },
    "constraints": [
      "(0<=user_choice)&&(user_choice<5)",
      "user_choice==98"
    ],
    "executionTime": 0
  },
  {
    "pathId": 100,
    "symbolicInputs": {
      "user_choice": 99
    },
    "constraints": [
      "(0<=user_choice)&&(user_choice<5)",
      "user_choice==99"
    ],
    "executionTime": 6
  }
]
